MANIFEST.in
README.rst
setup.cfg
setup.py
examples/Bas_tutorial.py
examples/__init__.py
examples/project_path.py
examples/tutorial_AW_omp_removal.py
research/BAR_Functions_AH.py
research/Bas_QA_testing.py
research/Bas_tutorial.py
research/ModPath_tests_SR.py
research/__init__.py
research/implementation_testing_for_greta.py
research/klad_py.py
research/model_structure_overview_2021-04-01.py
research/modpath_dictionaries_for_steven.py
research/notebook_modpath_tests.py
research/phreatic_implementation.py
research/phreatic_implementation_example.py
research/project_path.py
research/semi_confined_implementation.py
research/semi_confined_implementation_exmaple.py
research/set_cwd_to_project_root.py
sutra2/Analytical_Well.py
sutra2/ModPath_Well.py
sutra2/Transport_Removal.py
sutra2/__init__.py
sutra2/project_path.py
sutra2/removal_functions.py
sutra2.egg-info/PKG-INFO
sutra2.egg-info/SOURCES.txt
sutra2.egg-info/dependency_links.txt
sutra2.egg-info/requires.txt
sutra2.egg-info/top_level.txt
testing/__init__.py
testing/check_npgrids.py
testing/project_path.py
testing/test_ModPath_functions.py
testing/test_jupnb.py
testing/test_removal_functions.py
testing/test_transatomic.py