Metadata-Version: 2.1
Name: sutra2
Version: 0.6
Summary: A python package for correction, validation and analysis of ground water quality samples
Home-page: https://github.com/KWR-Water/sutra2
Author: KWR Water Research Institute
Author-email: martin.korevaar@kwrwater.nl, martin.van.der.schans@kwrwater.nl, alex.hocking@kwrwater.nl, steven.ros@kwrwater.nl
License: MIT
Download-URL: https://github.com/KWR-Water/sutra2/archive/refs/tags/v_01.tar.gz
Project-URL: Source, https://github.com/KWR-Water/sutra2
Project-URL: Documentation, http://sutra2.readthedocs.io/en/latest/
Project-URL: Tracker, https://github.com/KWR-Water/sutra2/issues
Project-URL: Help, https://github.com/KWR-Water/sutra2/issues
Platform: UNKNOWN
Classifier: Development Status :: 4 - Beta
Classifier: Intended Audience :: Science/Research
Classifier: Intended Audience :: Other Audience
Classifier: License :: OSI Approved :: MIT License
Classifier: Programming Language :: Python :: 3.6
Classifier: Programming Language :: Python :: 3.7
Classifier: Topic :: Scientific/Engineering :: Hydrology
Requires-Python: >=3.6
